attax
