Metadata-Version: 2.1
Name: attax
Version: 0.0.2
Summary: Attax: adversarial attacks using JAX
Home-page: https://github.com/jonasrauber/attax
Author: Jonas Rauber
Author-email: jonas.rauber@bethgelab.org
License: UNKNOWN
Platform: UNKNOWN
Classifier: Development Status :: 3 - Alpha
Classifier: Intended Audience :: Developers
Classifier: Intended Audience :: Science/Research
Classifier: License :: OSI Approved :: MIT License
Classifier: Programming Language :: Python :: 3
Classifier: Programming Language :: Python :: 3.6
Classifier: Topic :: Scientific/Engineering :: Artificial Intelligence
Provides-Extra: testing
